Workbook

Sheet Parámetros
A1: Magíster en Metodologías BIM - 2027-1
A2: Años | B2: 2027 | C2: 2028
A3: Arancel anual | B3: 3937500 | C3: 3937500
A4: Matrícula | B4: 192150 | C4: 201758
A5: Valor Hora Docencia Honorario | B5: 35000 | C5: 35000
A6: Valor Hora Docencia Reemplazo (carta de compromiso) | B6: 23152.5 | C6: 24310.125
A7: Valor Docencia Tesista | C7: 262500
A8: Año y semestre de inicio | B8: 2027-1S
A9: Descuento 1 | B9: 0.25 | C9: =+B9 -> 0.25
A10: Descuento 2 | B10: 0.3 | C10: =+B10 -> 0.3
A11: Incobrables | B11: 0.15 | C11: 0.15
A12: Over Head Central | B12: 0.2 | C12: 0.2
A13: Over Head Facultad | B13: 0.1 | C13: 0.1
A14: Director Programa | B14: 4152675 | C14: =+ROUNDUP(B14*1.05,0) -> 4360309
A15: Asistente de Dirección | B15: 2100000 | C15: =+ROUNDUP(B15*1.05,0) -> 2205000
A16: Tutoría Académica Canvas | B16: 1050000 | C16: =+ROUNDUP(B16*1.05,0) -> 1102500

Sheet Flujo estudiantes
A1: Flujo Estudiantes
A2: CONCEPTOS | B2: año 2027 | C2: año 2028
A3: Sin descuento | B3: 4 | C3: =+B3 -> 4
A4: Descuento 25% | B4: 5 | C4: =+B4 -> 5
A5: Descuento 30% | B5: 3 | C5: =+B5 -> 3
A6: Estudiantes totales | B6: =SUM(B3:B5) -> 12 | C6: =SUM(C3:C5) -> 12
A7: Graduación (al año 2) | B7: =0 -> 0 | C7: =C6 -> 12
A8: Ingresos matrícula | B8: =B6*Parámetros!$B$4 -> 2305800 | C8: =C6*Parámetros!$C$4 -> 2421096
A9: Ingresos arancel sin descuento | B9: =(B3)*Parámetros!$B$3 -> 15750000 | C9: =(C3)*Parámetros!$C$3 -> 15750000
A10: Ingresos arancel descuento 15% | B10: =(B4)*Parámetros!$B$3*(1-Parámetros!$B$9) -> 14765625 | C10: =(C4)*Parámetros!$C$3*(1-Parámetros!$C$9) -> 14765625
A11: Ingresos arancel descuento 25% | B11: =(B5)*Parámetros!$B$3*(1-Parámetros!$B$10) -> 8268750 | C11: =(C5)*Parámetros!$C$3*(1-Parámetros!$C$10) -> 8268750
A12: Ingresos arancel total | B12: =SUM(B9:B11) -> 38784375 | C12: =SUM(C9:C11) -> 38784375

Sheet Costo Directo de Docencia
A2: DETALLE DE HORAS DIRECTAS
A3: Semestre | B3: Asignatura | C3: Semanas | D3: Secciones | E3: Horas 2027 | F3: Horas 2028 | G3: 2027 | H3: 2028
A4: 1 | B4: Investigación Aplicada a Industria AEC | C4: 18 | D4: 1 | E4: 2 | F4: 0 | G4: =+$C$4*$D$4*E4 -> 36 | H4: =+$C$4*$D$4*F4 -> 0
A5: 1 | B5: Teoría del BIM y Políticas Públicas | C5: 18 | D5: 1 | E5: 2 | F5: 0 | G5: =+$C$4*$D$4*E5 -> 36 | H5: =+$C$4*$D$4*F5 -> 0
A6: 1 | B6: Modelamiento BIM | C6: 18 | D6: 1 | E6: 4 | F6: 0 | G6: =+$C$4*$D$4*E6 -> 72 | H6: =+$C$4*$D$4*F6 -> 0
A7: 1 | B7: Sustentabilidad y Certificación de Proyectos | C7: 18 | D7: 1 | E7: 2 | F7: 0 | G7: =+$C$4*$D$4*E7 -> 36 | H7: =+$C$4*$D$4*F7 -> 0
A8: 2 | B8: BIM para Arquitectura | C8: 18 | D8: 1 | E8: 4 | F8: 0 | G8: =+$C$4*$D$4*E8 -> 72 | H8: =+$C$4*$D$4*F8 -> 0
A9: 2 | B9: BIM para Ingeniería | C9: 18 | D9: 1 | E9: 2 | F9: 0 | G9: =+$C$4*$D$4*E9 -> 36 | H9: =+$C$4*$D$4*F9 -> 0
A10: 2 | B10: BIM para Construcción | C10: 18 | D10: 1 | E10: 2 | F10: 0 | G10: =+$C$4*$D$4*E10 -> 36 | H10: =+$C$4*$D$4*F10 -> 0
A11: 2 | B11: Manufactura Avanzada | C11: 18 | D11: 1 | E11: 2 | F11: 0 | G11: =+$C$4*$D$4*E11 -> 36 | H11: =+$C$4*$D$4*F11 -> 0
A12: 3 | B12: Programación en BIM | C12: 18 | D12: 1 | E12: 0 | F12: 2 | G12: =+$C$4*$D$4*E12 -> 0 | H12: =+$C$4*$D$4*F12 -> 36
A13: 3 | B13: Interoperabilidad | C13: 18 | D13: 1 | E13: 0 | F13: 4 | G13: =+$C$4*$D$4*E13 -> 0 | H13: =+$C$4*$D$4*F13 -> 72
A14: 3 | B14: Estándares y Roles | C14: 18 | D14: 1 | E14: 0 | F14: 2 | G14: =+$C$4*$D$4*E14 -> 0 | H14: =+$C$4*$D$4*F14 -> 36
A15: 3 | B15: Dirección y Formulación de Proyectos I+D+i | C15: 18 | D15: 1 | E15: 0 | F15: 2 | G15: =+$C$4*$D$4*E15 -> 0 | H15: =+$C$4*$D$4*F15 -> 36
A16: 4 | B16: Trabajo de Graduación | C16: 18 | D16: 1 | E16: 0 | F16: 4 | G16: =+$C$4*$D$4*E16 -> 0 | H16: =+$C$4*$D$4*F16 -> 72
B17: Suma | G17: =SUM(G4:G16) -> 360 | H17: =SUM(H4:H16) -> 252
B18: Suma Valorizada | G18: =+G17*Parámetros!B5 -> 12600000 | H18: =+H17*Parámetros!C5 -> 8820000
A20: DOCENCIA TESISTA / TRABAJO DE GRADUACIÓN
A21: Concepto | B21: Base estudiantes 2028 | C21: Valor unitario 2028 | D21: Costo 2028
A22: Docente tesista | B22: =+'Flujo estudiantes'!C7 -> 12 | C22: =+Parámetros!C7 -> 262500 | D22: =B22*C22 -> 3150000

Sheet FLUJO TOTAL
A1: Magíster en Metodologías BIM (2027-1)
A3: DETALLE | B3: 2027 | C3: 2028
A4: Matrícula | B4: ='Flujo estudiantes'!B8 -> 2305800 | C4: ='Flujo estudiantes'!C8 -> 2421096
A5: Aranceles | B5: ='Flujo estudiantes'!B12 -> 38784375 | C5: ='Flujo estudiantes'!C12 -> 38784375
A6: Incobrables (15%) | B6: =-B5*Parámetros!B11 -> -5817656.2 | C6: =-C5*Parámetros!C11 -> -5817656.2
A7: INGRESOS TOTAL | B7: =SUM(B5:B6) -> 32966719 | C7: =SUM(C5:C6) -> 32966719
A8: Docentes convenio | B8: =-'Costo Directo de Docencia'!G18 -> -12600000 | C8: =-'Costo Directo de Docencia'!H18 -> -8820000
A9: Docentes hora de reemplazo | B9: =0 -> 0 | C9: =0 -> 0
A10: Docente tesista | B10: =0 -> 0 | C10: =-'Flujo estudiantes'!C6*Parámetros!$C$7 -> -3150000
A11: COSTOS ACADÉMICOS | B11: =SUM(B8:B10) -> -12600000 | C11: =SUM(C8:C10) -> -11970000
A12: Director programa | B12: =-'Prorrateo Staff'!F4 -> -2076337.5 | C12: =-'Prorrateo Staff'!F7 -> -4360309
A13: Asistente de Dirección | B13: =-'Prorrateo Staff'!F13 -> -1050000 | C13: =-'Prorrateo Staff'!F16 -> -2205000
A14: Honorarios Charlas Vinculación Empresas | B14: -1000000 | C14: -1000000
A15: Tutoría Académica de seguimiento en Canvas | B15: =-'Prorrateo Staff'!F22 -> -525000 | C15: =-'Prorrateo Staff'!F25 -> -1102500
A16: HONORARIOS NO ACADÉMICOS | B16: =SUM(B12:B15) -> -4651337.5 | C16: =SUM(C12:C15) -> -8667809
A17: Materiales básicos de enseñanza | B17: 0 | C17: 0
A18: Textos impresos | B18: 0 | C18: 0
A19: LIBROS Y PUBLICACIONES TÉCNICAS | B19: =SUM(B17:B18) -> 0 | C19: =SUM(C17:C18) -> 0
A20: Difusión propia del programa | B20: 0 | C20: 0
A21: DIFUSIÓN | B21: =SUM(B20) -> 0 | C21: =SUM(C20) -> 0
A22: Pasajes nacionales e internacionales | B22: -1000000 | C22: 0
A23: Hospedaje nacional e internacional | B23: -1000000 | C23: 0
A24: PASAJES Y FLETES | B24: =SUM(B22:B23) -> -2000000 | C24: =SUM(C22:C23) -> 0
A25: Viáticos honorarios | B25: 0 | C25: 0
A26: VIÁTICOS HONORARIOS NACIONALES | B26: =SUM(B25) -> 0 | C26: =SUM(C25) -> 0
A27: Licencias de software | B27: -500000 | C27: -500000
A28: ADQUISICIÓN DE PROGRAMAS O LICENCIAS | B28: =SUM(B27) -> -500000 | C28: =SUM(C27) -> -500000
A29: Giro para rendir (gastos menores) | B29: 0 | C29: 0
A30: Coffee break | B30: -500000 | C30: -500000
A31: OTROS SERVICIOS | B31: =SUM(B29:B30) -> -500000 | C31: =SUM(C29:C30) -> -500000
A32: Becas por pasantías | B32: -4000000 | C32: 0
A33: AYUDAS INTERNAS | B33: =SUM(B32) -> -4000000 | C33: =SUM(C32) -> 0
A34: Over Head Central | B34: =-$B$7*Parámetros!B12 -> -6593343.8 | C34: =-$C$7*Parámetros!C12 -> -6593343.8
A35: Over Head Facultad | B35: =-$B$7*Parámetros!B13 -> -3296671.9 | C35: =-$C$7*Parámetros!C13 -> -3296671.9
A36: RETENCIONES | B36: =SUM(B34:B35) -> -9890015.6 | C36: =SUM(C34:C35) -> -9890015.6
A37: TOTAL COSTOS Y GASTOS DE ADM. | B37: =SUM(B11,B16,B19,B21,B24,B26,B28,B31,B33,B36) -> -34141353 | C37: =SUM(C11,C16,C19,C21,C24,C26,C28,C31,C33,C36) -> -31527825
A38: FLUJO DE CAJA NETO | B38: =+B7+B37 -> -1174634.4 | C38: =+C7+C37 -> 1438894.1
A39: Arrastre inicial anual | B39: 0 | C39: =+B40 -> -1174634.4
A40: SALDO FINAL ACUMULADO | B40: =+SUM(B38:B39) -> -1174634.4 | C40: =+SUM(C38:C39) -> 264259.75
A41: RENDIMIENTO OPERACIONAL | B41: =(B7+B37)/B7 -> -0.035630916 | C41: =(C7+C37)/C7 -> 0.043646871

Sheet Prorrateo Staff
A2: Dirección del programa
A3: Año | B3: Cohorte | C3: Situación durante el año | D3: Semestres activos | E3: Valor por semestre activo | F3: Monto prorrateado
A4: 2027 | B4: Cohorte 2026 | C4: Primer y segundo semestre 2027 | D4: 0.5 | E4: =+$C$6/$D$6 -> 4152675 | F4: =D4*E4 -> 2076337.5
A5: 2027 | B5: Cohorte 2027 | C5: Primer y segundo semestre 2027 | D5: 0.5 | E5: =+$C$6/$D$6 -> 4152675 | F5: =D5*E5 -> 2076337.5
A6: 2027 | B6: Total 2027 | C6: =+Parámetros!B14 -> 4152675 | D6: =SUM(D4:D5) -> 1 | F6: =SUM(F4:F5) -> 4152675
A7: 2028 | B7: Cohorte 2027 | C7: Primer y segundo semestre 2028 | D7: 1 | E7: =+$C$9/$D$9 -> 4360309 | F7: =D7*E7 -> 4360309
A8: 2028 | B8: Cohorte 2028 | C8: Primer y segundo semestre 2028 | D8: 0 | E8: =+$C$9/$D$9 -> 4360309 | F8: =D8*E8 -> 0
A9: 2028 | B9: Total 2028 | C9: =+Parámetros!C14 -> 4360309 | D9: =SUM(D7:D8) -> 1 | F9: =SUM(F7:F8) -> 4360309
A11: Asistente de Dirección
A12: Año | B12: Cohorte | C12: Situación durante el año | D12: Semestres activos | E12: Valor por semestre activo | F12: Monto prorrateado
A13: 2027 | B13: Cohorte 2026 | C13: Primer y segundo semestre 2027 | D13: 0.5 | E13: =+$C$15/$D$15 -> 2100000 | F13: =D13*E13 -> 1050000
A14: 2027 | B14: Cohorte 2027 | C14: Primer y segundo semestre 2027 | D14: 0.5 | E14: =+$C$15/$D$15 -> 2100000 | F14: =D14*E14 -> 1050000
A15: 2027 | B15: Total 2027 | C15: =+Parámetros!B15 -> 2100000 | D15: =SUM(D13:D14) -> 1 | F15: =SUM(F13:F14) -> 2100000
A16: 2028 | B16: Cohorte 2027 | C16: Primer y segundo semestre 2028 | D16: 1 | E16: =$C$18/$D$18 -> 2205000 | F16: =D16*E16 -> 2205000
A17: 2028 | B17: Cohorte 2028 | C17: Primer y segundo semestre 2028 | D17: 0 | E17: =$C$18/$D$18 -> 2205000 | F17: =D17*E17 -> 0
A18: 2028 | B18: Total 2028 | C18: =+Parámetros!C15 -> 2205000 | D18: =SUM(D16:D17) -> 1 | F18: =SUM(F16:F17) -> 2205000
A20: Tutoría Académica de seguimiento en Canvas
A21: Año | B21: Cohorte | C21: Situación durante el año | D21: Semestres activos | E21: Valor por semestre activo | F21: Monto prorrateado
A22: 2027 | B22: Cohorte 2026 | C22: Primer y segundo semestre 2027 | D22: 0.5 | E22: =+$C$24/$D$24 -> 1050000 | F22: =D22*E22 -> 525000
A23: 2027 | B23: Cohorte 2027 | C23: Primer y segundo semestre 2027 | D23: 0.5 | E23: =+$C$24/$D$24 -> 1050000 | F23: =D23*E23 -> 525000
A24: 2027 | B24: Total 2027 | C24: =+Parámetros!B16 -> 1050000 | D24: =SUM(D22:D23) -> 1 | F24: =SUM(F22:F23) -> 1050000
A25: 2028 | B25: Cohorte 2027 | C25: Primer y segundo semestre 2028 | D25: 1 | E25: =$C$27/$D$27 -> 1102500 | F25: =D25*E25 -> 1102500
A26: 2028 | B26: Cohorte 2028 | C26: Primer y segundo semestre 2028 | D26: 0 | E26: =$C$27/$D$27 -> 1102500 | F26: =D26*E26 -> 0
A27: 2028 | B27: Total 2028 | C27: =+Parámetros!C16 -> 1102500 | D27: =SUM(D25:D26) -> 1 | F27: =SUM(F25:F26) -> 1102500
